wrs2_py/__init__.py
wrs2_py/anova.py
wrs2_py/compare_groups.py
wrs2_py/correlation.py
wrs2_py/location.py
wrs2_py/utils.py
wrs2_py-0.1.0.dist-info/METADATA
wrs2_py-0.1.0.dist-info/WHEEL
wrs2_py-0.1.0.dist-info/top_level.txt
wrs2_py-0.1.0.dist-info/RECORD
