Metadata-Version: 2.4
Name: wrs2-py
Version: 0.1.0
Summary: A Python port of the WRS2 R package for robust statistical methods.
Author: Eichi Uehara
Classifier: Programming Language :: Python :: 3
Classifier: License :: OSI Approved :: MIT License
Classifier: Operating System :: OS Independent
Classifier: Topic :: Scientific/Engineering :: Mathematics
Requires-Python: >=3.8
Requires-Dist: numpy
Requires-Dist: scipy
